scripts/__init__.py
scripts/check_links.py
scripts/helper.py
scripts/melusina_projects.py
testpypi_pzhu-1.0.0.dist-info/METADATA
testpypi_pzhu-1.0.0.dist-info/WHEEL
testpypi_pzhu-1.0.0.dist-info/top_level.txt
testpypi_pzhu-1.0.0.dist-info/RECORD
