Metadata-Version: 2.1
Name: testpypi-pzhu
Version: 1.0.0
Summary: First PyPI package for testing
Author: Pin ZHU
Author-email: pin.zhu@uni.lu
